meme/__init__.py
meme/generate.py
meme/utils.py
meme/static/impact.ttf
meme_python-1.0.4.dist-info/LICENSE
meme_python-1.0.4.dist-info/METADATA
meme_python-1.0.4.dist-info/WHEEL
meme_python-1.0.4.dist-info/top_level.txt
meme_python-1.0.4.dist-info/RECORD
