Metadata-Version: 2.1
Name: meme-python
Version: 1.0.4
Summary: Meme Generator
Home-page: https://github.com/GabeMillikan/meme-python
Author: Gabe Millikan
License: MIT
Classifier: Development Status :: 4 - Beta
Classifier: License :: OSI Approved :: MIT License
Classifier: Programming Language :: Python :: 3
Requires-Python: >=3
License-File: LICENSE
Requires-Dist: Pillow
